tests/__init__.py
tests/test_new_norm.py
tinkt/__init__.py
tinkt/cm.py
tinkt/cmap_utils.py
tinkt/klasses/__init__.py
tinkt/klasses/color_map.py
tinkt/klasses/color_norm.py
tinkt/klasses/color_spec.py
tinkt-0.0.10.dist-info/DESCRIPTION.rst
tinkt-0.0.10.dist-info/METADATA
tinkt-0.0.10.dist-info/RECORD
tinkt-0.0.10.dist-info/WHEEL
tinkt-0.0.10.dist-info/metadata.json
tinkt-0.0.10.dist-info/top_level.txt
