Metadata-Version: 2.0
Name: tinkt
Version: 0.0.10
Summary: color and colormap utils (for matplotlib)
Home-page: https://github.com/claydodo/tinkt
Author: claydodo and his little friends (xiao huo ban)
Author-email: claydodo@foxmail.com
License: UNKNOWN
Platform: UNKNOWN
Classifier: Programming Language :: Python :: 2.7 
Classifier: Operating System :: OS Independent
Requires-Dist: konfluence (>=0.0.1)
Requires-Dist: krux
